jsontest.py
JsonTest-1.4.dist-info/LICENSE.md
JsonTest-1.4.dist-info/METADATA
JsonTest-1.4.dist-info/WHEEL
JsonTest-1.4.dist-info/top_level.txt
JsonTest-1.4.dist-info/RECORD
