Metadata-Version: 2.1
Name: JsonTest
Version: 1.4
Summary: A tiny metaclass for autogenerating tests from JSON files
Home-page: http://github.com/Fizzadar/JsonTest
Author: Nick Barrett
Author-email: pointlessrambler@gmail.com
License: UNKNOWN
Platform: UNKNOWN
